cellsino/__init__.py
cellsino/_version.py
cellsino/_version_save.py
cellsino/fluorescence.py
cellsino/sinogram.py
cellsino/elements/__init__.py
cellsino/elements/base_element.py
cellsino/elements/el_sphere.py
cellsino/phantoms/__init__.py
cellsino/phantoms/base_phantom.py
cellsino/phantoms/ph_simple_cell.py
cellsino/propagators/__init__.py
cellsino/propagators/base_propagator.py
cellsino/propagators/pp_projection.py
cellsino/propagators/pp_rytov.py
cellsino-0.5.0.dist-info/LICENSE
cellsino-0.5.0.dist-info/METADATA
cellsino-0.5.0.dist-info/WHEEL
cellsino-0.5.0.dist-info/top_level.txt
cellsino-0.5.0.dist-info/RECORD
