Metadata-Version: 2.1
Name: cellsino
Version: 0.5.0
Summary: in-silico sinograms (phase and fluorescence) of cells
Home-page: https://github.com/RI-imaging/cellsino
Author: Paul Müller
Author-email: dev@craban.de
License: MIT
Keywords: phase microscopy,fluorescence imaging,optical tomography,diffraction tomography
Platform: ALL
Classifier: Operating System :: OS Independent
Classifier: Programming Language :: Python :: 3
Classifier: Intended Audience :: Science/Research
Requires-Python: >=3.6, <4
Requires-Dist: flimage
Requires-Dist: h5py (>=2.7.0)
Requires-Dist: qpimage
Requires-Dist: qpsphere (>=0.5.0)
Requires-Dist: numpy (>=1.12.0)
